wink_sdk_affiliate_winklinks/__init__.py
wink_sdk_affiliate_winklinks/api_client.py
wink_sdk_affiliate_winklinks/api_response.py
wink_sdk_affiliate_winklinks/configuration.py
wink_sdk_affiliate_winklinks/exceptions.py
wink_sdk_affiliate_winklinks/py.typed
wink_sdk_affiliate_winklinks/rest.py
wink_sdk_affiliate_winklinks/api/__init__.py
wink_sdk_affiliate_winklinks/api/syndicated_item_api.py
wink_sdk_affiliate_winklinks/api/syndication_category_api.py
wink_sdk_affiliate_winklinks/api/syndication_consumer_api.py
wink_sdk_affiliate_winklinks/api/syndication_publisher_api.py
wink_sdk_affiliate_winklinks/api/syndication_settings_api.py
wink_sdk_affiliate_winklinks/models/__init__.py
wink_sdk_affiliate_winklinks/models/aggregate_descriptor_non_authenticated_entity.py
wink_sdk_affiliate_winklinks/models/application_context.py
wink_sdk_affiliate_winklinks/models/application_context_class_loader.py
wink_sdk_affiliate_winklinks/models/application_context_class_loader_parent.py
wink_sdk_affiliate_winklinks/models/application_context_class_loader_parent_defined_packages_inner.py
wink_sdk_affiliate_winklinks/models/application_context_class_loader_parent_unnamed_module.py
wink_sdk_affiliate_winklinks/models/application_context_class_loader_parent_unnamed_module_descriptor.py
wink_sdk_affiliate_winklinks/models/application_context_non_authenticated_entity.py
wink_sdk_affiliate_winklinks/models/application_context_non_authenticated_entity_class_loader.py
wink_sdk_affiliate_winklinks/models/application_context_non_authenticated_entity_class_loader_parent.py
wink_sdk_affiliate_winklinks/models/application_context_non_authenticated_entity_class_loader_parent_defined_packages_inner.py
wink_sdk_affiliate_winklinks/models/application_context_non_authenticated_entity_class_loader_parent_unnamed_module.py
wink_sdk_affiliate_winklinks/models/application_context_non_authenticated_entity_class_loader_parent_unnamed_module_class_loader.py
wink_sdk_affiliate_winklinks-0.0.57.dist-info/licenses/LICENSE
wink_sdk_affiliate_winklinks-0.0.57.dist-info/METADATA
wink_sdk_affiliate_winklinks-0.0.57.dist-info/WHEEL
wink_sdk_affiliate_winklinks-0.0.57.dist-info/top_level.txt
wink_sdk_affiliate_winklinks-0.0.57.dist-info/RECORD
